odoo/addons/mgmtsystem_action_efficacy/README.rst
odoo/addons/mgmtsystem_action_efficacy/__init__.py
odoo/addons/mgmtsystem_action_efficacy/__manifest__.py
odoo/addons/mgmtsystem_action_efficacy/i18n/es.po
odoo/addons/mgmtsystem_action_efficacy/i18n/fa.po
odoo/addons/mgmtsystem_action_efficacy/i18n/it.po
odoo/addons/mgmtsystem_action_efficacy/i18n/mgmtsystem_action_efficacy.pot
odoo/addons/mgmtsystem_action_efficacy/models/__init__.py
odoo/addons/mgmtsystem_action_efficacy/models/mgmtsystem_action.py
odoo/addons/mgmtsystem_action_efficacy/readme/CONTRIBUTORS.md
odoo/addons/mgmtsystem_action_efficacy/readme/DESCRIPTION.md
odoo/addons/mgmtsystem_action_efficacy/readme/HISTORY.md
odoo/addons/mgmtsystem_action_efficacy/readme/USAGE.md
odoo/addons/mgmtsystem_action_efficacy/static/description/icon.png
odoo/addons/mgmtsystem_action_efficacy/static/description/index.html
odoo/addons/mgmtsystem_action_efficacy/tests/__init__.py
odoo/addons/mgmtsystem_action_efficacy/tests/test_efficacy.py
odoo/addons/mgmtsystem_action_efficacy/views/mgmtsystem_action_views.xml
odoo_addon_mgmtsystem_action_efficacy-18.0.1.0.0.3.dist-info/METADATA
odoo_addon_mgmtsystem_action_efficacy-18.0.1.0.0.3.dist-info/WHEEL
odoo_addon_mgmtsystem_action_efficacy-18.0.1.0.0.3.dist-info/top_level.txt
odoo_addon_mgmtsystem_action_efficacy-18.0.1.0.0.3.dist-info/RECORD
