Metadata-Version: 2.1
Name: odoo-addon-mgmtsystem_action_efficacy
Version: 18.0.1.0.0.3
Requires-Python: >=3.10
Requires-Dist: odoo-addon-mgmtsystem_action==18.0.*
Requires-Dist: odoo==18.0.*
Summary: Add information on the application of the Action.
Home-page: https://github.com/OCA/management-system
License: AGPL-3
Author: Associazione PNLUG - Gruppo Odoo, Odoo Community Association (OCA)
Author-email: support@odoo-community.org
Classifier: Programming Language :: Python
Classifier: Framework :: Odoo
Classifier: Framework :: Odoo :: 18.0
Classifier: License :: OSI Approved :: GNU Affero General Public License v3
Classifier: Development Status :: 4 - Beta
